polymerfingerprint/__init__.py
polymerfingerprint/_types.py
polymerfingerprint/core.py
polymerfingerprint/datareader.py
polymerfingerprint/fingerprints.py
polymerfingerprint/loader.py
polymerfingerprint/logger.py
polymerfingerprint/polymer_SMILES_parser.py
polymerfingerprint/utils.py
polymerfingerprint-1.0.0.dist-info/METADATA
polymerfingerprint-1.0.0.dist-info/WHEEL
polymerfingerprint-1.0.0.dist-info/top_level.txt
polymerfingerprint-1.0.0.dist-info/RECORD
