Metadata-Version: 2.4
Name: polymerfingerprint
Version: 1.0.0
Summary: create fingerprints for polymers
Requires-Python: >=3.11
Requires-Dist: numpy>=2.2.5
Requires-Dist: pandas>=2.2.3
Requires-Dist: rdkit>=2024.9.6
Requires-Dist: tqdm>=4.67.1
